Metadata-Version: 2.1
Name: qvrpy
Version: 0.1a0
Summary: An abstraction of the QVR Pro API
Home-page: https://github.com/DasUberLeo/qvrpy
Author: Grant Patterson
Author-email: patterson.grant@gmail.com
License: UNKNOWN
Download-URL: https://github.com/DasUberLeo/qvrpy/archive/v0.1-alpha.tar.gz
Keywords: QVR Pro,QVRPro,QNAP,IoT,Surveillance
Platform: UNKNOWN
Classifier: Development Status :: 3 - Alpha
Classifier: Intended Audience :: Developers
Classifier: License :: OSI Approved :: MIT License
Classifier: Natural Language :: English
Classifier: Operating System :: OS Independent
Classifier: Programming Language :: Python :: 3.6
Classifier: Topic :: Home Automation
Classifier: Topic :: System :: Hardware
Requires-Python: >=3.6
